crawly/__init__.py
crawly/crawly.py
crawly_zarcuel-1.0.0.dist-info/licenses/LICENSE
crawly_zarcuel-1.0.0.dist-info/METADATA
crawly_zarcuel-1.0.0.dist-info/WHEEL
crawly_zarcuel-1.0.0.dist-info/entry_points.txt
crawly_zarcuel-1.0.0.dist-info/top_level.txt
crawly_zarcuel-1.0.0.dist-info/RECORD
