Metadata-Version: 2.4
Name: crawly-zarcuel
Version: 1.0.0
Summary: A privacy-focused web scanner that detects cookies and trackers.
Home-page: https://github.com/Zarcuel/Crawly
Author: Zarcuel
Author-email: zarcuelkali@gmail.com
License: MIT
Classifier: Programming Language :: Python :: 3
Classifier: License :: OSI Approved :: MIT License
Classifier: Operating System :: OS Independent
Requires-Python: >=3.7
License-File: LICENSE
Requires-Dist: beautifulsoup4
Requires-Dist: playwright
Dynamic: author
Dynamic: author-email
Dynamic: classifier
Dynamic: description
Dynamic: description-content-type
Dynamic: home-page
Dynamic: license
Dynamic: license-file
Dynamic: requires-dist
Dynamic: requires-python
Dynamic: summary
